{
  "project_info": {
    "project_number": "21653421615",
    "firebase_url": "https://modernlandiom.firebaseio.com",
    "project_id": "modernlandiom",
    "storage_bucket": "modernlandiom.appspot.com"
  },
  "client": [
    {
      "client_info": {
        "mobilesdk_app_id": "1:21653421615:android:0e1eac4919a3f5873ed0da",
        "android_client_info": {
          "package_name": "approval.modernland.co.id"
        }
      },
      "oauth_client": [
        {
          "client_id": "21653421615-2im2cnc0phrd33ck07qs9fp0qannnkv2.apps.googleusercontent.com",
          "client_type": 1,
          "android_info": {
            "package_name": "approval.modernland.co.id",
            "certificate_hash": "6ab787081208354434878edd4193d880d12526dd"
          }
        },
        {
          "client_id": "21653421615-ufuvjh2tcnpmtnkl2sosm5s3pjb81tru.apps.googleusercontent.com",
          "client_type": 3
        }
      ],
      "api_key": [
        {
          "current_key": "AIzaSyBcGxtiDd-iI92ZNAlAjYAXNkHBBkK0HTs"
        }
      ],
      "services": {
        "appinvite_service": {
          "other_platform_oauth_client": [
            {
              "client_id": "21653421615-ufuvjh2tcnpmtnkl2sosm5s3pjb81tru.apps.googleusercontent.com",
              "client_type": 3
            },
            {
              "client_id": "21653421615-0gdd00pru84japun9qe23c9iov99r49r.apps.googleusercontent.com",
              "client_type": 2,
              "ios_info": {
                "bundle_id": "com.modernland.modernland-approval"
              }
            }
          ]
        }
      }
    },
    {
      "client_info": {
        "mobilesdk_app_id": "1:21653421615:android:5945f76d1154e4633ed0da",
        "android_client_info": {
          "package_name": "com.modernland.signflowx"
        }
      },
      "oauth_client": [
        {
          "client_id": "21653421615-ufuvjh2tcnpmtnkl2sosm5s3pjb81tru.apps.googleusercontent.com",
          "client_type": 3
        }
      ],
      "api_key": [
        {
          "current_key": "AIzaSyBcGxtiDd-iI92ZNAlAjYAXNkHBBkK0HTs"
        }
      ],
      "services": {
        "appinvite_service": {
          "other_platform_oauth_client": [
            {
              "client_id": "21653421615-ufuvjh2tcnpmtnkl2sosm5s3pjb81tru.apps.googleusercontent.com",
              "client_type": 3
            },
            {
              "client_id": "21653421615-0gdd00pru84japun9qe23c9iov99r49r.apps.googleusercontent.com",
              "client_type": 2,
              "ios_info": {
                "bundle_id": "com.modernland.modernland-approval"
              }
            }
          ]
        }
      }
    },
    {
      "client_info": {
        "mobilesdk_app_id": "1:21653421615:android:4bd4db420bcb5ad63ed0da",
        "android_client_info": {
          "package_name": "iom.modernland.co.id"
        }
      },
      "oauth_client": [
        {
          "client_id": "21653421615-u0outr5ctgvbb1cg2umq162aj0jft126.apps.googleusercontent.com",
          "client_type": 1,
          "android_info": {
            "package_name": "iom.modernland.co.id",
            "certificate_hash": "6bc394334f6be2eaa669f64fcf88175cab3eaa62"
          }
        },
        {
          "client_id": "21653421615-umfc8qvcvpg3i6rf7kj49dldl88v56nj.apps.googleusercontent.com",
          "client_type": 1,
          "android_info": {
            "package_name": "iom.modernland.co.id",
            "certificate_hash": "8288b4be3f63e3f3d60b79bd1a416d9c23ef55be"
          }
        },
        {
          "client_id": "21653421615-ufuvjh2tcnpmtnkl2sosm5s3pjb81tru.apps.googleusercontent.com",
          "client_type": 3
        }
      ],
      "api_key": [
        {
          "current_key": "AIzaSyBcGxtiDd-iI92ZNAlAjYAXNkHBBkK0HTs"
        }
      ],
      "services": {
        "appinvite_service": {
          "other_platform_oauth_client": [
            {
              "client_id": "21653421615-ufuvjh2tcnpmtnkl2sosm5s3pjb81tru.apps.googleusercontent.com",
              "client_type": 3
            },
            {
              "client_id": "21653421615-0gdd00pru84japun9qe23c9iov99r49r.apps.googleusercontent.com",
              "client_type": 2,
              "ios_info": {
                "bundle_id": "com.modernland.modernland-approval"
              }
            }
          ]
        }
      }
    }
  ],
  "configuration_version": "1"
}